memcord/__init__.py
memcord/archival.py
memcord/batch_operations.py
memcord/cache.py
memcord/compression.py
memcord/errors.py
memcord/feedback_messages.py
memcord/handler_registry.py
memcord/importer.py
memcord/logging_config.py
memcord/memory_manager.py
memcord/merger.py
memcord/models.py
memcord/optimized_schemas.py
memcord/optimized_server.py
memcord/progress_integration.py
memcord/progress_tracker.py
memcord/prompts.py
memcord/query.py
memcord/response_builder.py
memcord/response_optimizer.py
memcord/search.py
memcord/security.py
memcord/server.py
memcord/smart_defaults.py
memcord/status_monitoring.py
memcord/storage.py
memcord/storage_efficiency.py
memcord/summarizer.py
memcord/temporal_parser.py
memcord/workflow_templates.py
memcord/services/__init__.py
memcord/services/archive_service.py
memcord/services/compression_service.py
memcord/services/import_service.py
memcord/services/merge_service.py
memcord/services/monitoring_service.py
memcord/services/select_entry_service.py
iflow_mcp_ukkit_memcord-2.4.1.dist-info/METADATA
iflow_mcp_ukkit_memcord-2.4.1.dist-info/WHEEL
iflow_mcp_ukkit_memcord-2.4.1.dist-info/entry_points.txt
iflow_mcp_ukkit_memcord-2.4.1.dist-info/licenses/LICENSE
iflow_mcp_ukkit_memcord-2.4.1.dist-info/RECORD
